CHANGES.rst
LICENSE
MANIFEST.in
README.rst
setup.py
ipdetailscache.egg-info/PKG-INFO
ipdetailscache.egg-info/SOURCES.txt
ipdetailscache.egg-info/dependency_links.txt
ipdetailscache.egg-info/namespace_packages.txt
ipdetailscache.egg-info/requires.txt
ipdetailscache.egg-info/top_level.txt
pierky/__init__.py
pierky/ipdetailscache/__init__.py
pierky/ipdetailscache/version.py