Metadata-Version: 1.1
Name: ipdetailscache
Version: 0.4.8
Summary: A Python library to gather IP address details (ASN, prefix, resource holder, reverse DNS) using the RIPEStat API
Home-page: https://github.com/pierky/ipdetailscache
Author: Pier Carlo Chiodi
Author-email: pierky@pierky.com
License: MIT
Download-URL: https://github.com/pierky/ipdetailscache
Keywords: RIPE,RIPE NCC,RIPE Stat,Library,IPv4,IPv6,IP address
Platform: UNKNOWN
Classifier: Development Status :: 4 - Beta
Classifier: Intended Audience :: Developers
Classifier: Intended Audience :: Information Technology
Classifier: Intended Audience :: System Administrators
Classifier: License :: OSI Approved :: MIT License
Classifier: Operating System :: POSIX
Classifier: Operating System :: Unix
Classifier: Programming Language :: Python
Classifier: Programming Language :: Python :: 2.7
Classifier: Programming Language :: Python :: 3.4
Classifier: Topic :: Software Development :: Libraries :: Python Modules
Classifier: Topic :: Internet :: WWW/HTTP
Classifier: Topic :: System :: Networking
